{
   "availableAreas":{
      "org.kaaproject.configuration.unchangedT":"unchanged"
   },
   "areas":{
      "array":[
         {
            "name":{
               "string":"Europe"
            },
            "cities":{
               "array":[
                  {
                     "name":{
                        "string":"Amsterdam"
                     },
                     "places":{
                        "array":[
                           {
                              "category":{
                                 "org.kaaproject.kaa.demo.cityguide.Category":"HOTEL"
                              },
                              "title":{
                                 "string":"Marriott Amsterdam"
                              },
                              "photoUrl":{
                                 "string":"http://media-cdn.tripadvisor.com/media/photo-f/06/fd/e7/c4/deluxe-guest-room.jpg"
                              },
                              "description":{
                                 "string":"Known for its colourful tulips and peaceful canals, Netherland's capital charms every visitor. In the midst of this beautiful city, Amsterdam Marriott Hotel welcomes guests with exceptional service. Just across from Leidseplein, the city centre hotel is ideally located for dining and entertainment as well as fashionable shopping."
                              },
                              "location":{
                                 "org.kaaproject.kaa.demo.cityguide.Location":{
                                    "latitude":{
                                       "double":52.363291
                                    },
                                    "longitude":{
                                       "double":4.880761
                                    },
                                    "__uuid": null
                                 }
                              },
                              "__uuid": null
                           },
                           {
                              "category":{
                                 "org.kaaproject.kaa.demo.cityguide.Category":"HOTEL"
                              },
                              "title":{
                                 "string":"Renaissance Amsterdam Hotel"
                              },
                              "photoUrl":{
                                 "string":"http://media-cdn.tripadvisor.com/media/photo-f/06/fe/03/b6/king-guest-room.jpg"
                              },
                              "description":{
                                 "string":"Just a short walk from Central Station and situated in the historic city centre of charming Amsterdam, the Renaissance Amsterdam Hotel is the top spot to be after a top-to-bottom redesign. Our contemporary hotel in Amsterdam offers a warm and welcoming lobby, renovated guest accommodations featuring Renaissance Bedding, broadband internet access and HDTV."
                              },
                              "location":{
                                 "org.kaaproject.kaa.demo.cityguide.Location":{
                                    "latitude":{
                                       "double":52.378064
                                    },
                                    "longitude":{
                                       "double":4.894593
                                    },
                                    "__uuid": null
                                 }
                              },
                              "__uuid": null
                           },
                           {
                              "category":{
                                 "org.kaaproject.kaa.demo.cityguide.Category":"HOTEL"
                              },
                              "title":{
                                 "string":"Crowne Plaza Amsterdam City Centre"
                              },
                              "photoUrl":{
                                 "string":"http://media-cdn.tripadvisor.com/media/photo-f/06/66/df/f2/crowne-plaza-amsterdam.jpg"
                              },
                              "description":{
                                 "string":"Book a Club Room or Suite at the Crowne Plaza Amsterdam City Centre hotel and gain access to the exclusive club lounge. Club guests enjoy browsing complimentary newspapers over breakfast, and return to use complimentary high-speed Internet and evening snacks and drinks."
                              },
                              "location":{
                                 "org.kaaproject.kaa.demo.cityguide.Location":{
                                    "latitude":{
                                       "double":52.377476
                                    },
                                    "longitude":{
                                       "double":4.895767
                                    },
                                    "__uuid": null
                                 }
                              },
                              "__uuid": null
                           },
                           {
                              "category":{
                                 "org.kaaproject.kaa.demo.cityguide.Category":"SHOP"
                              },
                              "title":{
                                 "string":"Van Stapele Koekmakerij"
                              },
                              "photoUrl":{
                                 "string":"http://media-cdn.tripadvisor.com/media/photo-s/05/9a/c0/d5/van-stapele-koekmakerij.jpg"
                              },
                              "description":{
                                 "string":"The cosy, warm atmosphere of our shop will briefly take you back to the Amsterdam of olden days. The aroma of freshly baked cookies slowly drifts towards you as soft piano music fills the air, and light reflected through crystal chandeliers sparkles down on rows of delicious cookies."
                              },
                              "location":{
                                 "org.kaaproject.kaa.demo.cityguide.Location":{
                                    "latitude":{
                                       "double":52.368953
                                    },
                                    "longitude":{
                                       "double":4.888423
                                    },
                                    "__uuid": null
                                 }
                              },
                              "__uuid": null
                           },
                           {
                              "category":{
                                 "org.kaaproject.kaa.demo.cityguide.Category":"SHOP"
                              },
                              "title":{
                                 "string":"Bonebakker Jeweler Amsterdam"
                              },
                              "photoUrl":{
                                 "string":"http://media-cdn.tripadvisor.com/media/photo-s/06/63/b6/82/bonebakker-jeweler-amsterdam.jpg"
                              },
                              "description":{
                                 "string":"Bonebakker\u2019s Jewellery store is situated in the monumental Van Baerle Shopping Gallery in the charming Museum Quarter in Amsterdam.  Bonebakker has created an attractive, sophisticated venue for connoisseurs and lovers of jewellery within the luxurious atmosphere of the Conservatorium Hotel. Blending the delicate ornaments of the 19th century Art-Nouveau palace with state-of-the art interior features, Bonebakker Jeweller evokes an elegant atmosphere in an intimate setting."
                              },
                              "location":{
                                 "org.kaaproject.kaa.demo.cityguide.Location":{
                                    "latitude":{
                                       "double":52.358783
                                    },
                                    "longitude":{
                                       "double":4.878607
                                    },
                                    "__uuid": null
                                 }
                              },
                              "__uuid": null
                           },
                           {
                              "category":{
                                 "org.kaaproject.kaa.demo.cityguide.Category":"SHOP"
                              },
                              "title":{
                                 "string":"Chocolatl"
                              },
                              "photoUrl":{
                                 "string":"http://media-cdn.tripadvisor.com/media/photo-s/02/5d/42/55/chocolatl-store.jpg"
                              },
                              "description":{
                                 "string":"Chocolatl is a specialty retail chocolate shop located in Amsterdam, Netherlands. Opened in December 2010, we like to think of the shop as a kind of  \u201cchocolate gallery\u201d through which we seek to promote and make available high quality chocolate from around the world."
                              },
                              "location":{
                                 "org.kaaproject.kaa.demo.cityguide.Location":{
                                    "latitude":{
                                       "double":52.370568
                                    },
                                    "longitude":{
                                       "double":4.880011
                                    },
                                    "__uuid": null
                                 }
                              },
                              "__uuid": null
                           },
                           {
                              "category":{
                                 "org.kaaproject.kaa.demo.cityguide.Category":"MUSEUM"
                              },
                              "title":{
                                 "string":"The Rijksmuseum (National Museum)"
                              },
                              "photoUrl":{
                                 "string":"http://media-cdn.tripadvisor.com/media/photo-s/00/1c/d3/57/view-from-museumplein.jpg"
                              },
                              "description":{
                                 "string":"The Rijksmuseum is the museum of the Netherlands. The completely renovated Rijksmuseum tells the story of the Netherlands from the Middle Ages to the 20th century. Including works by Rembrandt, Vermeer, Frans Hals, and more! Most famous is Rembrandt's masterpiece the Night Watch. A new display of the collection, a renewed building, new public facilities, a revamped garden and a new Asian Pavilion. Open daily from 9 am to 5 pm."
                              },
                              "location":{
                                 "org.kaaproject.kaa.demo.cityguide.Location":{
                                    "latitude":{
                                       "double":52.360517
                                    },
                                    "longitude":{
                                       "double":4.881597
                                    },
                                    "__uuid": null
                                 }
                              },
                              "__uuid": null
                           },
                           {
                              "category":{
                                 "org.kaaproject.kaa.demo.cityguide.Category":"MUSEUM"
                              },
                              "title":{
                                 "string":"Anne Frank House (Anne Frankhuis)"
                              },
                              "photoUrl":{
                                 "string":"http://media-cdn.tripadvisor.com/media/photo-s/01/58/c2/a4/caption.jpg"
                              },
                              "description":{
                                 "string":"A Museum with a Story. Visit the hiding place where Anne Frank wrote her diary during the Second World War. For more than two years, Anne Frank lived secretively with the other people in hiding in the back part of her father\u2019s office building at # 263 Prinsengracht. "
                              },
                              "location":{
                                 "org.kaaproject.kaa.demo.cityguide.Location":{
                                    "latitude":{
                                       "double":52.375208
                                    },
                                    "longitude":{
                                       "double":4.883997
                                    },
                                    "__uuid": null
                                 }
                              },
                              "__uuid": null
                           },
                           {
                              "category":{
                                 "org.kaaproject.kaa.demo.cityguide.Category":"MUSEUM"
                              },
                              "title":{
                                 "string":"Van Gogh Museum"
                              },
                              "photoUrl":{
                                 "string":"http://media-cdn.tripadvisor.com/media/photo-s/01/8b/bf/c1/museum.jpg"
                              },
                              "description":{
                                 "string":"The world's largest collection from the Dutch painter Vincent van Gogh (1853-1890) features more than 200 paintings and 600 drawings. "
                              },
                              "location":{
                                 "org.kaaproject.kaa.demo.cityguide.Location":{
                                    "latitude":{
                                       "double":52.358419
                                    },
                                    "longitude":{
                                       "double":4.881055
                                    },
                                    "__uuid": null
                                 }
                              },
                              "__uuid": null
                           },
                           {
                              "category":{
                                 "org.kaaproject.kaa.demo.cityguide.Category":"RESTAURANT"
                              },
                              "title":{
                                 "string":"Restaurant Johannes"
                              },
                              "photoUrl":{
                                 "string":"http://media-cdn.tripadvisor.com/media/photo-l/06/2d/9f/ad/restaurant-johannes.jpg"
                              },
                              "description":{
                                 "string":"Chef Tommy den Hartog, restaurant manager Aline Mannes and their team are looking forward to welcoming you at Johannes were they found the perfect place to share their enthusiasm."
                              },
                              "location":{
                                 "org.kaaproject.kaa.demo.cityguide.Location":{
                                    "latitude":{
                                       "double":52.3676
                                    },
                                    "longitude":{
                                       "double":4.887301
                                    },
                                    "__uuid": null
                                 }
                              },
                              "__uuid": null
                           },
                           {
                              "category":{
                                 "org.kaaproject.kaa.demo.cityguide.Category":"RESTAURANT"
                              },
                              "title":{
                                 "string":"Lombardo's"
                              },
                              "photoUrl":{
                                 "string":"http://media-cdn.tripadvisor.com/media/photo-s/05/af/d1/b9/lombardo-s.jpg"
                              },
                              "description":{
                                 "string":"It's all about taste!! Thats our motto... The Best Burgers, sandwiches, salads, freshly made juices...And damn good coffee! Served with a smile and a whole lot of love! We are located near the Rijksmuseum in the vibrant Spiegel quarter. We are near the corner of Kerkstraat and N. Spiegelstraat, careful you might miss it!! It's cozy at Lombardo's...So seating is always first come first served. Come in for the 4 years uncontested BEST burgers in Amsterdam!!"
                              },
                              "location":{
                                 "org.kaaproject.kaa.demo.cityguide.Location":{
                                    "latitude":{
                                       "double":52.363524
                                    },
                                    "longitude":{
                                       "double":4.888665
                                    },
                                    "__uuid": null
                                 }
                              },
                              "__uuid": null
                           },
                           {
                              "category":{
                                 "org.kaaproject.kaa.demo.cityguide.Category":"RESTAURANT"
                              },
                              "title":{
                                 "string":"Bord'Eau"
                              },
                              "photoUrl":{
                                 "string":"http://media-cdn.tripadvisor.com/media/photo-s/04/4f/4b/af/bord-eau.jpg"
                              },
                              "description":{
                                 "string":"Recently Michelin star awarded Bord'Eau offers a culinary adventure directed by Executive Chef Richard van Oostenbrugge and Sous Chef Thomas Groot. Exceptional ingredients are blended to create symphonies of flavour, all complemented by the finest wines from around the globe. The intimacy of the salon-like setting, the classical simplicity of the decor and the grace and attentiveness of the service suggest high style and privilege overlooking the Amstel River."
                              },
                              "location":{
                                 "org.kaaproject.kaa.demo.cityguide.Location":{
                                    "latitude":{
                                       "double":52.3676
                                    },
                                    "longitude":{
                                       "double":4.894391
                                    },
                                    "__uuid": null
                                 }
                              },
                              "__uuid": null
                           }
                        ]
                     },
                     "__uuid": null
                  }
               ]
            },
            "__uuid": null
         }
      ]
   },
   "__uuid": null
}